bio_pyminer-0.11.0.data/scripts/cell_signals.py
bio_pyminer-0.11.0.data/scripts/clustering.py
bio_pyminer-0.11.0.data/scripts/combine_gprofiler_results.py
bio_pyminer-0.11.0.data/scripts/common_functions.py
bio_pyminer-0.11.0.data/scripts/get_degrees_of_separation_from_adjacency_list.py
bio_pyminer-0.11.0.data/scripts/get_high_marker_genes.py
bio_pyminer-0.11.0.data/scripts/get_stats.py
bio_pyminer-0.11.0.data/scripts/make_website.py
bio_pyminer-0.11.0.data/scripts/mat_to_adj_list.py
bio_pyminer-0.11.0.data/scripts/plot_gene_subset.py
bio_pyminer-0.11.0.data/scripts/plot_network.py
bio_pyminer-0.11.0.data/scripts/pyminer.py
bio_pyminer-0.11.0.data/scripts/pyminer_analyze_communities.py
bio_pyminer-0.11.0.data/scripts/pyminer_analyze_pathologic_genes.py
bio_pyminer-0.11.0.data/scripts/pyminer_annotate_variants_to_genes.py
bio_pyminer-0.11.0.data/scripts/pyminer_bayes.py
bio_pyminer-0.11.0.data/scripts/pyminer_cell_graph_plotting.py
bio_pyminer-0.11.0.data/scripts/pyminer_clust_funcs.py
bio_pyminer-0.11.0.data/scripts/pyminer_common_stats_functions.py
bio_pyminer-0.11.0.data/scripts/pyminer_continuous_lineage_pseudotime.py
bio_pyminer-0.11.0.data/scripts/pyminer_convert_to_scanpy.py
bio_pyminer-0.11.0.data/scripts/pyminer_ensembl_rest.py
bio_pyminer-0.11.0.data/scripts/pyminer_feature_selection.py
bio_pyminer-0.11.0.data/scripts/pyminer_gene_term_comentions.py
bio_pyminer-0.11.0.data/scripts/pyminer_get_dispersion.py
bio_pyminer-0.11.0.data/scripts/pyminer_get_stats.py
bio_pyminer-0.11.0.data/scripts/pyminer_global_test.py
bio_pyminer-0.11.0.data/scripts/pyminer_gprofile.py
bio_pyminer-0.11.0.data/scripts/pyminer_gprofiler_converter.py
bio_pyminer-0.11.0.data/scripts/pyminer_h5_to_tab.py
bio_pyminer-0.11.0.data/scripts/pyminer_objs.py
bio_pyminer-0.11.0.data/scripts/pyminer_process_tad_bed.py
bio_pyminer-0.11.0.data/scripts/pyminer_recursive_clust.py
bio_pyminer-0.11.0.data/scripts/pyminer_tm_norm.py
bio_pyminer-0.11.0.data/scripts/tab_to_h5.py
bio_pyminer-0.11.0.dist-info/METADATA
bio_pyminer-0.11.0.dist-info/WHEEL
bio_pyminer-0.11.0.dist-info/top_level.txt
bio_pyminer-0.11.0.dist-info/RECORD
