Metadata-Version: 2.1
Name: bio-pyminer
Version: 0.11.0
Summary: PyMINEr: automated biologic insights from large datasets.
Home-page: https://scottyler892@bitbucket.org/scottyler892/pyminer
Author: Scott Tyler
Author-email: scottyler89@gmail.com
License: UNKNOWN
Platform: UNKNOWN
Classifier: Programming Language :: Python :: 3
Classifier: License :: OSI Approved :: GNU Affero General Public License v3
Classifier: Operating System :: OS Independent
Requires-Dist: Pillow (>=5.4)
Requires-Dist: networkx (>=2.4)
Requires-Dist: seaborn (>=0.8.1)
Requires-Dist: numpy (>=1.16.0)
Requires-Dist: scikit-learn
Requires-Dist: h5py (>=2.9.0)
Requires-Dist: matplotlib (>=3.0.2)
Requires-Dist: scipy (>=1.2.0)
Requires-Dist: gprofiler-official (==0.3.5)
Requires-Dist: umap-learn
Requires-Dist: python-louvain
Requires-Dist: statsmodels (==0.9.0)
Requires-Dist: pandas
Requires-Dist: beautifulsoup4
Requires-Dist: six (>=0.13.0)
Requires-Dist: ray (>=0.8.0)
Requires-Dist: fastcluster
Requires-Dist: bio-pyminer-norm
